seleniumprint/__init__.py
seleniumprint/selenium_pdf.py
seleniumprint/utility_wrapper.py
seleniumprint/drivers/__init__.py
seleniumprint/drivers/chrome_pdf_driver.py
seleniumprint/drivers/i_selenium_pdf_driver.py
selenium_print-1.0.2.dist-info/LICENSE
selenium_print-1.0.2.dist-info/METADATA
selenium_print-1.0.2.dist-info/WHEEL
selenium_print-1.0.2.dist-info/top_level.txt
selenium_print-1.0.2.dist-info/RECORD
