Metadata-Version: 2.1
Name: selenium-print
Version: 1.0.2
Summary: A minimal printing utility based on selenium and chrome that is able to render any HTML to PDF.
Home-page: https://github.com/bubblegumsoldier/selenium-print
Author: Henry Müssemann
Author-email: henry@muessemann.de
License: MIT
Keywords: print,pdf,converter,selenium
Platform: UNKNOWN
License-File: LICENSE
Requires-Dist: selenium
